{"decade":1970,"franchise":"Detroit Tigers","franchiseId":"DET","hitters":[{"display":{"2B":12,"3B":1,"AB":246,"AVG":"0.313","BB":40,"G":90,"H":77,"HBP":3,"HR":20,"OPS":"1.028","PA":290,"SO":33,"team":"DET","year":1979},"name":"Champ Summers","playerId":"summech01","pos":["OF","RF","DH"],"vector":{"b1":0.137415,"b2":0.04501,"b3":0.002684,"bb":0.137221,"hr":0.087982,"out":0.589688}},{"display":{"2B":2,"3B":3,"AB":195,"AVG":"0.338","BB":21,"G":82,"H":66,"HBP":2,"HR":11,"OPS":"0.957","PA":218,"SO":17,"team":"DET","year":1971},"name":"Gates Brown","playerId":"brownga01","pos":["LF","OF"],"vector":{"b1":0.21899,"b2":0.012261,"b3":0.014124,"bb":0.093598,"hr":0.073492,"out":0.587535}},{"display":{"2B":26,"3B":3,"AB":490,"AVG":"0.318","BB":68,"G":134,"H":156,"HBP":2,"HR":26,"OPS":"0.941","PA":570,"SO":70,"team":"DET","year":1979},"name":"Steve Kemp","playerId":"kempst01","pos":["OF","LF","DH"],"vector":{"b1":0.161046,"b2":0.049792,"b3":0.004111,"bb":0.114051,"hr":0.058396,"out":0.612604}},{"display":{"2B":4,"3B":0,"AB":98,"AVG":"0.316","BB":19,"G":38,"H":31,"HBP":1,"HR":4,"OPS":"0.912","PA":121,"SO":18,"team":"DET","year":1972},"name":"Duke Sims","playerId":"simsdu01","pos":["C"],"vector":{"b1":0.187448,"b2":0.046066,"b3":0.0,"bb":0.160269,"hr":0.059069,"out":0.547148}},{"display":{"2B":10,"3B":3,"AB":452,"AVG":"0.283","BB":59,"G":135,"H":128,"HBP":7,"HR":32,"OPS":"0.903","PA":523,"SO":86,"team":"DET","year":1971},"name":"Norm Cash","playerId":"cashno01","pos":["1B"],"vector":{"b1":0.151816,"b2":0.025602,"b3":0.005898,"bb":0.112168,"hr":0.089286,"out":0.61523}},{"display":{"2B":8,"3B":1,"AB":238,"AVG":"0.298","BB":21,"G":72,"H":71,"HBP":3,"HR":15,"OPS":"0.891","PA":263,"SO":36,"team":"DET","year":1974},"name":"Willie Horton","playerId":"hortowi01","pos":["LF","OF"],"vector":{"b1":0.159171,"b2":0.039049,"b3":0.003476,"bb":0.086633,"hr":0.091419,"out":0.620252}},{"display":{"2B":19,"3B":2,"AB":405,"AVG":"0.294","BB":82,"G":133,"H":119,"HBP":7,"HR":15,"OPS":"0.878","PA":501,"SO":57,"team":"DET","year":1971},"name":"Al Kaline","playerId":"kalinal01","pos":["OF","RF"],"vector":{"b1":0.158496,"b2":0.050783,"b3":0.004105,"bb":0.157913,"hr":0.043694,"out":0.585009}},{"display":{"2B":5,"3B":0,"AB":94,"AVG":"0.287","BB":13,"G":56,"H":27,"HBP":1,"HR":4,"OPS":"0.844","PA":113,"SO":26,"team":"DET","year":1970},"name":"Ike Brown","playerId":"brownik01","pos":["2B"],"vector":{"b1":0.159321,"b2":0.060803,"b3":0.0,"bb":0.110688,"hr":0.046284,"out":0.622904}},{"display":{"2B":17,"3B":5,"AB":445,"AVG":"0.297","BB":42,"G":130,"H":132,"HBP":5,"HR":18,"OPS":"0.840","PA":502,"SO":44,"team":"DET","year":1974},"name":"Bill Freehan","playerId":"freehbi01","pos":["1B","C"],"vector":{"b1":0.165207,"b2":0.043999,"b3":0.009217,"bb":0.089959,"hr":0.058169,"out":0.633449}},{"display":{"2B":30,"3B":10,"AB":652,"AVG":"0.325","BB":37,"G":154,"H":212,"HBP":4,"HR":16,"OPS":"0.838","PA":698,"SO":121,"team":"DET","year":1977},"name":"Ron LeFlore","playerId":"lefloro01","pos":["CF","OF"],"vector":{"b1":0.204976,"b2":0.048714,"b3":0.009548,"bb":0.055436,"hr":0.029324,"out":0.652002}},{"display":{"2B":25,"3B":3,"AB":589,"AVG":"0.287","BB":74,"G":153,"H":169,"HBP":0,"HR":26,"OPS":"0.836","PA":669,"SO":96,"team":"DET","year":1978},"name":"Jason Thompson","playerId":"thompja01","pos":["1B"],"vector":{"b1":0.157118,"b2":0.042972,"b3":0.003541,"bb":0.103361,"hr":0.058968,"out":0.63404}},{"display":{"2B":14,"3B":7,"AB":404,"AVG":"0.307","BB":38,"G":119,"H":124,"HBP":1,"HR":12,"OPS":"0.832","PA":447,"SO":41,"team":"DET","year":1973},"name":"Jim Northrup","playerId":"northji01","pos":["OF","RF","LF","CF"],"vector":{"b1":0.185543,"b2":0.039835,"b3":0.014374,"bb":0.078083,"hr":0.038486,"out":0.643679}},{"display":{"2B":8,"3B":1,"AB":164,"AVG":"0.274","BB":14,"G":53,"H":45,"HBP":0,"HR":9,"OPS":"0.831","PA":178,"SO":18,"team":"DET","year":1977},"name":"John Wockenfuss","playerId":"wockejo01","pos":["C"],"vector":{"b1":0.138917,"b2":0.050867,"b3":0.003739,"bb":0.074122,"hr":0.064589,"out":0.667766}},{"display":{"2B":28,"3B":3,"AB":589,"AVG":"0.299","BB":83,"G":161,"H":176,"HBP":7,"HR":15,"OPS":"0.818","PA":690,"SO":49,"team":"DET","year":1976},"name":"Rusty Staub","playerId":"staubru01","pos":["OF","RF","DH"],"vector":{"b1":0.168239,"b2":0.051394,"b3":0.003391,"bb":0.124199,"hr":0.042337,"out":0.61044}},{"display":{"2B":12,"3B":3,"AB":305,"AVG":"0.285","BB":11,"G":115,"H":87,"HBP":3,"HR":15,"OPS":"0.804","PA":325,"SO":44,"team":"DET","year":1976},"name":"Ben Oglivie","playerId":"oglivbe01","pos":["OF","RF","LF","CF"],"vector":{"b1":0.157582,"b2":0.047052,"b3":0.007243,"bb":0.041271,"hr":0.090442,"out":0.65641}},{"display":{"2B":18,"3B":1,"AB":343,"AVG":"0.274","BB":49,"G":106,"H":94,"HBP":1,"HR":12,"OPS":"0.804","PA":395,"SO":52,"team":"DET","year":1973},"name":"Dick McAuliffe","playerId":"mcauldi01","pos":["2B"],"vector":{"b1":0.145449,"b2":0.057993,"b3":0.002325,"bb":0.113352,"hr":0.043578,"out":0.637303}},{"display":{"2B":26,"3B":3,"AB":493,"AVG":"0.276","BB":49,"G":143,"H":136,"HBP":2,"HR":19,"OPS":"0.800","PA":548,"SO":105,"team":"DET","year":1979},"name":"Lance Parrish","playerId":"parrila02","pos":["C"],"vector":{"b1":0.146239,"b2":0.051893,"b3":0.004284,"bb":0.086601,"hr":0.044475,"out":0.666508}},{"display":{"2B":9,"3B":1,"AB":227,"AVG":"0.256","BB":24,"G":85,"H":58,"HBP":0,"HR":12,"OPS":"0.789","PA":251,"SO":28,"team":"DET","year":1973},"name":"Frank Howard","playerId":"howarfr01","pos":["DH"],"vector":{"b1":0.130135,"b2":0.045401,"b3":0.003641,"bb":0.08519,"hr":0.068232,"out":0.667401}},{"display":{"2B":14,"3B":8,"AB":423,"AVG":"0.286","BB":78,"G":127,"H":121,"HBP":1,"HR":3,"OPS":"0.774","PA":520,"SO":66,"team":"DET","year":1979},"name":"Lou Whitaker","playerId":"whitalo01","pos":["2B"],"vector":{"b1":0.17183,"b2":0.030096,"b3":0.012305,"bb":0.144486,"hr":0.007564,"out":0.633719}},{"display":{"2B":10,"3B":2,"AB":181,"AVG":"0.287","BB":12,"G":55,"H":52,"HBP":1,"HR":3,"OPS":"0.749","PA":196,"SO":11,"team":"DET","year":1971},"name":"Tony Taylor","playerId":"tayloto02","pos":["2B"],"vector":{"b1":0.1821,"b2":0.068887,"b3":0.010581,"bb":0.059448,"hr":0.022523,"out":0.656461}},{"display":{"2B":19,"3B":10,"AB":615,"AVG":"0.309","BB":38,"G":151,"H":190,"HBP":2,"HR":5,"OPS":"0.745","PA":673,"SO":61,"team":"DET","year":1977},"name":"Tito Fuentes","playerId":"fuentti01","pos":["2B"],"vector":{"b1":0.216467,"b2":0.032582,"b3":0.010083,"bb":0.057116,"hr":0.009677,"out":0.674075}},{"display":{"2B":6,"3B":1,"AB":170,"AVG":"0.235","BB":20,"G":53,"H":40,"HBP":2,"HR":8,"OPS":"0.743","PA":194,"SO":40,"team":"DET","year":1975},"name":"Jack Pierce","playerId":"piercja01","pos":["1B"],"vector":{"b1":0.118479,"b2":0.03816,"b3":0.004385,"bb":0.099568,"hr":0.061634,"out":0.677774}},{"display":{"2B":7,"3B":0,"AB":99,"AVG":"0.273","BB":5,"G":26,"H":27,"HBP":0,"HR":3,"OPS":"0.742","PA":105,"SO":20,"team":"DET","year":1974},"name":"Reggie Sanders","playerId":"sandere01","pos":["1B"],"vector":{"b1":0.145592,"b2":0.086406,"b3":0.0,"bb":0.045642,"hr":0.046237,"out":0.676123}},{"display":{"2B":8,"3B":0,"AB":213,"AVG":"0.296","BB":17,"G":95,"H":63,"HBP":1,"HR":4,"OPS":"0.739","PA":233,"SO":22,"team":"DET","year":1979},"name":"Lynn Jones","playerId":"jonesly01","pos":["OF","CF","RF","LF"],"vector":{"b1":0.199095,"b2":0.037509,"b3":0.0,"bb":0.071802,"hr":0.021995,"out":0.669599}},{"display":{"2B":14,"3B":5,"AB":401,"AVG":"0.292","BB":24,"G":139,"H":117,"HBP":0,"HR":7,"OPS":"0.733","PA":432,"SO":44,"team":"DET","year":1971},"name":"Mickey Stanley","playerId":"stanlmi01","pos":["CF","OF"],"vector":{"b1":0.202532,"b2":0.043612,"b3":0.011962,"bb":0.049631,"hr":0.023765,"out":0.668498}},{"display":{"2B":3,"3B":0,"AB":103,"AVG":"0.282","BB":6,"G":55,"H":29,"HBP":0,"HR":3,"OPS":"0.713","PA":111,"SO":9,"team":"DET","year":1977},"name":"Tim Corcoran","playerId":"corcoti01","pos":["OF"],"vector":{"b1":0.189765,"b2":0.030589,"b3":0.0,"bb":0.050941,"hr":0.034525,"out":0.69418}},{"display":{"2B":5,"3B":1,"AB":141,"AVG":"0.227","BB":15,"G":43,"H":32,"HBP":1,"HR":6,"OPS":"0.710","PA":159,"SO":26,"team":"DET","year":1974},"name":"Jim Nettles","playerId":"nettlji01","pos":["OF","RF"],"vector":{"b1":0.113463,"b2":0.040884,"b3":0.005824,"bb":0.09675,"hr":0.061257,"out":0.681822}},{"display":{"2B":8,"3B":0,"AB":222,"AVG":"0.275","BB":22,"G":88,"H":61,"HBP":2,"HR":4,"OPS":"0.709","PA":250,"SO":28,"team":"DET","year":1978},"name":"Phil Mankowski","playerId":"mankoph01","pos":["3B"],"vector":{"b1":0.181052,"b2":0.037189,"b3":0.0,"bb":0.09066,"hr":0.024535,"out":0.666564}},{"display":{"2B":5,"3B":0,"AB":138,"AVG":"0.254","BB":9,"G":83,"H":35,"HBP":1,"HR":5,"OPS":"0.703","PA":148,"SO":21,"team":"DET","year":1971},"name":"Dalton Jones","playerId":"jonesda03","pos":["OF","3B","LF"],"vector":{"b1":0.161283,"b2":0.045149,"b3":0.0,"bb":0.059943,"hr":0.049205,"out":0.68442}},{"display":{"2B":4,"3B":1,"AB":103,"AVG":"0.233","BB":19,"G":50,"H":24,"HBP":0,"HR":2,"OPS":"0.702","PA":124,"SO":24,"team":"DET","year":1974},"name":"Marv Lane","playerId":"lanema01","pos":["OF","LF"],"vector":{"b1":0.124111,"b2":0.04209,"b3":0.007494,"bb":0.14785,"hr":0.026277,"out":0.652178}},{"display":{"2B":17,"3B":5,"AB":447,"AVG":"0.257","BB":36,"G":129,"H":115,"HBP":4,"HR":10,"OPS":"0.700","PA":496,"SO":94,"team":"DET","year":1975},"name":"Leon Roberts","playerId":"roberle01","pos":["OF","RF"],"vector":{"b1":0.155417,"b2":0.042719,"b3":0.008663,"bb":0.071528,"hr":0.030441,"out":0.691232}},{"display":{"2B":25,"3B":2,"AB":385,"AVG":"0.265","BB":19,"G":134,"H":102,"HBP":3,"HR":7,"OPS":"0.698","PA":414,"SO":37,"team":"DET","year":1978},"name":"Aurelio Rodriguez","playerId":"rodriau01","pos":["3B"],"vector":{"b1":0.151736,"b2":0.070185,"b3":0.003856,"bb":0.050188,"hr":0.025929,"out":0.698106}},{"display":{"2B":13,"3B":4,"AB":258,"AVG":"0.248","BB":30,"G":109,"H":64,"HBP":3,"HR":3,"OPS":"0.697","PA":293,"SO":42,"team":"DET","year":1970},"name":"Elliott Maddox","playerId":"maddoel01","pos":["3B","OF","LF","SS"],"vector":{"b1":0.145377,"b2":0.059013,"b3":0.013479,"bb":0.097394,"hr":0.012958,"out":0.671779}},{"display":{"2B":1,"3B":1,"AB":88,"AVG":"0.307","BB":6,"G":55,"H":27,"HBP":0,"HR":0,"OPS":"0.692","PA":95,"SO":13,"team":"DET","year":1974},"name":"John Knox","playerId":"knoxjo01","pos":["2B"],"vector":{"b1":0.236883,"b2":0.013657,"b3":0.009727,"bb":0.060597,"hr":0.0,"out":0.679136}},{"display":{"2B":11,"3B":4,"AB":460,"AVG":"0.276","BB":43,"G":142,"H":127,"HBP":0,"HR":6,"OPS":"0.691","PA":520,"SO":55,"team":"DET","year":1979},"name":"Alan Trammell","playerId":"trammal01","pos":["SS"],"vector":{"b1":0.188982,"b2":0.023554,"b3":0.006129,"bb":0.078335,"hr":0.015068,"out":0.687932}},{"display":{"2B":9,"3B":0,"AB":178,"AVG":"0.242","BB":10,"G":91,"H":43,"HBP":0,"HR":7,"OPS":"0.691","PA":190,"SO":31,"team":"DET","year":1973},"name":"Dick Sharon","playerId":"sharodi01","pos":["OF","RF","LF"],"vector":{"b1":0.129618,"b2":0.060295,"b3":0.0,"bb":0.04714,"hr":0.052859,"out":0.710088}},{"display":{"2B":5,"3B":2,"AB":190,"AVG":"0.263","BB":11,"G":60,"H":50,"HBP":2,"HR":4,"OPS":"0.683","PA":208,"SO":40,"team":"DET","year":1979},"name":"Tom Brookens","playerId":"brookto01","pos":["3B","2B"],"vector":{"b1":0.173146,"b2":0.026661,"b3":0.007631,"bb":0.058974,"hr":0.025014,"out":0.708574}},{"display":{"2B":2,"3B":0,"AB":55,"AVG":"0.236","BB":5,"G":22,"H":13,"HBP":0,"HR":2,"OPS":"0.682","PA":60,"SO":8,"team":"DET","year":1974},"name":"Tom Veryzer","playerId":"veryzto01","pos":["SS"],"vector":{"b1":0.133602,"b2":0.042792,"b3":0.0,"bb":0.079113,"hr":0.05343,"out":0.691063}},{"display":{"2B":9,"3B":3,"AB":397,"AVG":"0.249","BB":26,"G":115,"H":99,"HBP":0,"HR":12,"OPS":"0.669","PA":438,"SO":31,"team":"DET","year":1977},"name":"Milt May","playerId":"maymi01","pos":["C"],"vector":{"b1":0.159736,"b2":0.023689,"b3":0.004643,"bb":0.056983,"hr":0.035649,"out":0.7193}},{"display":{"2B":8,"3B":0,"AB":152,"AVG":"0.263","BB":15,"G":63,"H":40,"HBP":0,"HR":1,"OPS":"0.665","PA":174,"SO":20,"team":"DET","year":1976},"name":"Bruce Kimm","playerId":"kimmbr01","pos":["C"],"vector":{"b1":0.16576,"b2":0.06067,"b3":0.0,"bb":0.085526,"hr":0.011662,"out":0.676382}},{"display":{"2B":3,"3B":0,"AB":146,"AVG":"0.274","BB":16,"G":75,"H":40,"HBP":0,"HR":1,"OPS":"0.657","PA":171,"SO":25,"team":"DET","year":1979},"name":"Mark Wagner","playerId":"wagnema01","pos":["SS","2B"],"vector":{"b1":0.198809,"b2":0.019898,"b3":0.0,"bb":0.090287,"hr":0.007779,"out":0.683227}},{"display":{"2B":2,"3B":0,"AB":54,"AVG":"0.241","BB":6,"G":29,"H":13,"HBP":1,"HR":1,"OPS":"0.656","PA":62,"SO":3,"team":"DET","year":1971},"name":"Jim Price","playerId":"priceji01","pos":["C"],"vector":{"b1":0.153999,"b2":0.04311,"b3":0.0,"bb":0.100162,"hr":0.023492,"out":0.679237}},{"display":{"2B":15,"3B":2,"AB":429,"AVG":"0.268","BB":19,"G":125,"H":115,"HBP":2,"HR":6,"OPS":"0.653","PA":457,"SO":49,"team":"DET","year":1976},"name":"Alex Johnson","playerId":"johnsal01","pos":["LF","OF","DH"],"vector":{"b1":0.180159,"b2":0.041661,"b3":0.00342,"bb":0.043851,"hr":0.025625,"out":0.705284}},{"display":{"2B":12,"3B":3,"AB":503,"AVG":"0.258","BB":45,"G":129,"H":130,"HBP":3,"HR":6,"OPS":"0.651","PA":559,"SO":41,"team":"DET","year":1975},"name":"Gary Sutherland","playerId":"suthega01","pos":["2B"],"vector":{"b1":0.180566,"b2":0.026677,"b3":0.004598,"bb":0.075936,"hr":0.016158,"out":0.696065}},{"display":{"2B":6,"3B":3,"AB":198,"AVG":"0.237","BB":11,"G":74,"H":47,"HBP":2,"HR":4,"OPS":"0.640","PA":215,"SO":38,"team":"DET","year":1974},"name":"Jerry Moses","playerId":"mosesje01","pos":["C"],"vector":{"b1":0.142174,"b2":0.036162,"b3":0.012878,"bb":0.057942,"hr":0.030101,"out":0.720743}},{"display":{"2B":3,"3B":0,"AB":95,"AVG":"0.221","BB":5,"G":30,"H":21,"HBP":0,"HR":4,"OPS":"0.639","PA":101,"SO":14,"team":"DET","year":1975},"name":"Billy Baldwin","playerId":"baldwbi01","pos":["OF","RF","CF"],"vector":{"b1":0.128715,"b2":0.037015,"b3":0.0,"bb":0.0439,"hr":0.059785,"out":0.730585}},{"display":{"2B":4,"3B":0,"AB":92,"AVG":"0.217","BB":7,"G":60,"H":20,"HBP":0,"HR":3,"OPS":"0.631","PA":100,"SO":19,"team":"DET","year":1974},"name":"Gene Lamont","playerId":"lamonge01","pos":["C"],"vector":{"b1":0.116958,"b2":0.051869,"b3":0.0,"bb":0.067126,"hr":0.048572,"out":0.715475}},{"display":{"2B":23,"3B":1,"AB":440,"AVG":"0.211","BB":30,"G":129,"H":93,"HBP":2,"HR":14,"OPS":"0.624","PA":482,"SO":56,"team":"DET","year":1979},"name":"Jerry Morales","playerId":"moralje01","pos":["OF","RF","CF","LF"],"vector":{"b1":0.103777,"b2":0.052121,"b3":0.001622,"bb":0.061696,"hr":0.037209,"out":0.743575}},{"display":{"2B":5,"3B":2,"AB":121,"AVG":"0.207","BB":15,"G":59,"H":25,"HBP":0,"HR":2,"OPS":"0.623","PA":139,"SO":14,"team":"DET","year":1972},"name":"Tom Haller","playerId":"halleto01","pos":["C"],"vector":{"b1":0.112314,"b2":0.049596,"b3":0.015765,"bb":0.103531,"hr":0.025438,"out":0.693356}},{"display":{"2B":8,"3B":4,"AB":294,"AVG":"0.252","BB":17,"G":105,"H":74,"HBP":0,"HR":2,"OPS":"0.618","PA":315,"SO":22,"team":"DET","year":1976},"name":"Dan Meyer","playerId":"meyerda01","pos":["LF","OF","1B"],"vector":{"b1":0.171724,"b2":0.032474,"b3":0.009998,"bb":0.051882,"hr":0.012484,"out":0.721438}},{"display":{"2B":15,"3B":3,"AB":502,"AVG":"0.221","BB":29,"G":153,"H":111,"HBP":3,"HR":14,"OPS":"0.613","PA":546,"SO":71,"team":"DET","year":1974},"name":"Ed Brinkman","playerId":"brinked01","pos":["SS"],"vector":{"b1":0.131031,"b2":0.035859,"b3":0.005108,"bb":0.056572,"hr":0.041788,"out":0.729642}},{"display":{"2B":13,"3B":0,"AB":363,"AVG":"0.218","BB":44,"G":128,"H":79,"HBP":4,"HR":6,"OPS":"0.610","PA":419,"SO":56,"team":"DET","year":1970},"name":"Don Wert","playerId":"wertdo01","pos":["3B"],"vector":{"b1":0.139823,"b2":0.041622,"b3":0.0,"bb":0.099917,"hr":0.018279,"out":0.700359}},{"display":{"2B":11,"3B":6,"AB":415,"AVG":"0.243","BB":18,"G":135,"H":101,"HBP":1,"HR":0,"OPS":"0.573","PA":451,"SO":39,"team":"DET","year":1970},"name":"Cesar Gutierrez","playerId":"gutiece01","pos":["SS"],"vector":{"b1":0.185449,"b2":0.033365,"b3":0.01351,"bb":0.037469,"hr":0.0,"out":0.730207}},{"display":{"2B":7,"3B":1,"AB":222,"AVG":"0.221","BB":19,"G":80,"H":49,"HBP":0,"HR":2,"OPS":"0.570","PA":244,"SO":34,"team":"DET","year":1976},"name":"Chuck Scrivener","playerId":"scrivch01","pos":["2B","SS"],"vector":{"b1":0.144504,"b2":0.036786,"b3":0.003236,"bb":0.075069,"hr":0.016162,"out":0.724243}},{"display":{"2B":1,"3B":0,"AB":59,"AVG":"0.136","BB":10,"G":29,"H":8,"HBP":0,"HR":3,"OPS":"0.562","PA":70,"SO":15,"team":"DET","year":1979},"name":"Al Greene","playerId":"greenal01","pos":["DH"],"vector":{"b1":0.051754,"b2":0.015539,"b3":0.0,"bb":0.132206,"hr":0.054674,"out":0.745827}},{"display":{"2B":2,"3B":0,"AB":74,"AVG":"0.230","BB":7,"G":32,"H":17,"HBP":0,"HR":0,"OPS":"0.553","PA":82,"SO":14,"team":"DET","year":1972},"name":"Paul Jata","playerId":"jatapa01","pos":["1B","OF"],"vector":{"b1":0.178091,"b2":0.033554,"b3":0.0,"bb":0.081717,"hr":0.0,"out":0.706638}},{"display":{"2B":5,"3B":2,"AB":130,"AVG":"0.223","BB":6,"G":56,"H":29,"HBP":0,"HR":0,"OPS":"0.550","PA":143,"SO":11,"team":"DET","year":1978},"name":"Steve Dillard","playerId":"dillast01","pos":["2B"],"vector":{"b1":0.147634,"b2":0.042214,"b3":0.011595,"bb":0.041164,"hr":0.0,"out":0.757393}},{"display":{"2B":3,"3B":1,"AB":66,"AVG":"0.197","BB":7,"G":39,"H":13,"HBP":0,"HR":0,"OPS":"0.547","PA":88,"SO":17,"team":"DET","year":1970},"name":"Joe Niekro","playerId":"niekrjo01","pos":["DH"],"vector":{"b1":0.118945,"b2":0.054473,"b3":0.013479,"bb":0.082637,"hr":0.0,"out":0.730466}},{"display":{"2B":2,"3B":0,"AB":145,"AVG":"0.214","BB":8,"G":56,"H":31,"HBP":0,"HR":3,"OPS":"0.543","PA":158,"SO":28,"team":"DET","year":1975},"name":"Gene Michael","playerId":"michage01","pos":["SS"],"vector":{"b1":0.155222,"b2":0.016024,"b3":0.0,"bb":0.045611,"hr":0.029116,"out":0.754027}},{"display":{"2B":10,"3B":2,"AB":227,"AVG":"0.198","BB":9,"G":77,"H":45,"HBP":4,"HR":3,"OPS":"0.538","PA":245,"SO":40,"team":"DET","year":1976},"name":"Pedro Garcia","playerId":"garcipe01","pos":["2B"],"vector":{"b1":0.110242,"b2":0.052119,"b3":0.006418,"bb":0.05094,"hr":0.024043,"out":0.756238}},{"display":{"2B":4,"3B":2,"AB":156,"AVG":"0.147","BB":17,"G":45,"H":23,"HBP":0,"HR":4,"OPS":"0.507","PA":173,"SO":52,"team":"DET","year":1975},"name":"Nate Colbert","playerId":"colbena01","pos":["1B"],"vector":{"b1":0.069087,"b2":0.028528,"b3":0.009834,"bb":0.086278,"hr":0.034558,"out":0.771715}},{"display":{"2B":2,"3B":0,"AB":62,"AVG":"0.226","BB":0,"G":20,"H":14,"HBP":0,"HR":0,"OPS":"0.480","PA":63,"SO":11,"team":"DET","year":1974},"name":"Ron Cash","playerId":"cashro01","pos":["1B"],"vector":{"b1":0.169653,"b2":0.040754,"b3":0.0,"bb":0.0,"hr":0.0,"out":0.789593}},{"display":{"2B":1,"3B":0,"AB":84,"AVG":"0.107","BB":12,"G":47,"H":9,"HBP":0,"HR":3,"OPS":"0.443","PA":98,"SO":29,"team":"DET","year":1970},"name":"Ken Szotkiewicz","playerId":"szotkke01","pos":["SS"],"vector":{"b1":0.049731,"b2":0.013665,"b3":0.0,"bb":0.106613,"hr":0.039007,"out":0.790984}},{"display":{"2B":1,"3B":0,"AB":102,"AVG":"0.137","BB":7,"G":59,"H":14,"HBP":0,"HR":2,"OPS":"0.399","PA":110,"SO":17,"team":"DET","year":1973},"name":"Rich Reese","playerId":"reeseri01","pos":["1B","LF","OF"],"vector":{"b1":0.091565,"b2":0.011616,"b3":0.0,"bb":0.057217,"hr":0.026187,"out":0.813415}},{"display":{"2B":1,"3B":0,"AB":68,"AVG":"0.162","BB":1,"G":29,"H":11,"HBP":0,"HR":1,"OPS":"0.395","PA":72,"SO":18,"team":"DET","year":1970},"name":"Les Cain","playerId":"cainle01","pos":["DH"],"vector":{"b1":0.125841,"b2":0.01921,"b3":0.0,"bb":0.01249,"hr":0.018279,"out":0.82418}},{"display":{"2B":2,"3B":0,"AB":115,"AVG":"0.130","BB":16,"G":45,"H":15,"HBP":1,"HR":0,"OPS":"0.390","PA":148,"SO":55,"team":"DET","year":1971},"name":"Mickey Lolich","playerId":"lolicmi01","pos":["DH"],"vector":{"b1":0.094033,"b2":0.020249,"b3":0.0,"bb":0.114254,"hr":0.0,"out":0.771464}},{"display":{"2B":0,"3B":0,"AB":44,"AVG":"0.136","BB":3,"G":35,"H":6,"HBP":1,"HR":0,"OPS":"0.345","PA":50,"SO":25,"team":"DET","year":1972},"name":"Tom Timmermann","playerId":"timmeto01","pos":["DH"],"vector":{"b1":0.120211,"b2":0.0,"b3":0.0,"bb":0.078799,"hr":0.0,"out":0.80099}},{"display":{"2B":0,"3B":0,"AB":82,"AVG":"0.110","BB":5,"G":40,"H":9,"HBP":0,"HR":0,"OPS":"0.271","PA":102,"SO":30,"team":"DET","year":1972},"name":"Joe Coleman","playerId":"colemjo05","pos":["DH"],"vector":{"b1":0.099485,"b2":0.0,"b3":0.0,"bb":0.054344,"hr":0.0,"out":0.846171}}],"pitchers":[{"allowed":{"b1":0.149534,"b2":0.043413,"b3":0.004824,"bb":0.084684,"hr":0.023062,"out":0.694483},"display":{"BB":31,"ERA":"2.06","G":16,"GS":14,"H":93,"HR":6,"IP":113.7,"L":3,"SO":72,"W":10,"team":"DET","year":1972},"name":"Woodie Fryman","playerId":"frymawo01","role":"SP","stamina":0.7894},{"allowed":{"b1":0.153138,"b2":0.044459,"b3":0.00494,"bb":0.058766,"hr":0.024275,"out":0.714422},"display":{"BB":53,"ERA":"2.34","G":31,"GS":29,"H":217,"HR":12,"IP":250.3,"L":9,"SO":97,"W":19,"team":"DET","year":1976},"name":"Mark Fidrych","playerId":"fidryma01","role":"SP","stamina":0.8973},{"allowed":{"b1":0.154058,"b2":0.044726,"b3":0.00497,"bb":0.067108,"hr":0.03949,"out":0.689648},"display":{"BB":74,"ERA":"2.50","G":41,"GS":41,"H":282,"HR":29,"IP":327.3,"L":14,"SO":250,"W":22,"team":"DET","year":1972},"name":"Mickey Lolich","playerId":"lolicmi01","role":"SP","stamina":0.8871},{"allowed":{"b1":0.135587,"b2":0.039364,"b3":0.004374,"bb":0.108393,"hr":0.036134,"out":0.676148},"display":{"BB":110,"ERA":"2.80","G":40,"GS":39,"H":216,"HR":23,"IP":280.0,"L":14,"SO":222,"W":19,"team":"DET","year":1972},"name":"Joe Coleman","playerId":"colemjo05","role":"SP","stamina":0.7778},{"allowed":{"b1":0.150254,"b2":0.043622,"b3":0.004847,"bb":0.077782,"hr":0.03349,"out":0.690005},"display":{"BB":30,"ERA":"2.81","G":14,"GS":13,"H":94,"HR":9,"IP":105.7,"L":7,"SO":49,"W":6,"team":"DET","year":1978},"name":"Kip Young","playerId":"youngki01","role":"SP","stamina":0.8386},{"allowed":{"b1":0.142799,"b2":0.041458,"b3":0.004606,"bb":0.078136,"hr":0.035156,"out":0.697845},"display":{"BB":41,"ERA":"2.89","G":34,"GS":25,"H":121,"HR":12,"IP":149.7,"L":10,"SO":88,"W":8,"team":"DET","year":1972},"name":"Tom Timmermann","playerId":"timmeto01","role":"SP","stamina":0.4891},{"allowed":{"b1":0.163631,"b2":0.047506,"b3":0.005278,"bb":0.047675,"hr":0.037054,"out":0.698856},"display":{"BB":34,"ERA":"3.09","G":28,"GS":28,"H":222,"HR":25,"IP":218.3,"L":7,"SO":92,"W":15,"team":"DET","year":1977},"name":"Dave Rozema","playerId":"rozemda01","role":"SP","stamina":0.8664},{"allowed":{"b1":0.165609,"b2":0.04808,"b3":0.005342,"bb":0.079755,"hr":0.021163,"out":0.680051},"display":{"BB":25,"ERA":"3.20","G":23,"GS":13,"H":74,"HR":4,"IP":81.7,"L":6,"SO":65,"W":5,"team":"DET","year":1972},"name":"Bill Slayback","playerId":"slaybbi01","role":"SP","stamina":0.3945},{"allowed":{"b1":0.145394,"b2":0.042211,"b3":0.00469,"bb":0.079094,"hr":0.031112,"out":0.697499},"display":{"BB":59,"ERA":"3.28","G":27,"GS":27,"H":179,"HR":19,"IP":197.7,"L":7,"SO":113,"W":17,"team":"DET","year":1979},"name":"Jack Morris","playerId":"morrija02","role":"SP","stamina":0.8134},{"allowed":{"b1":0.164466,"b2":0.047748,"b3":0.005305,"bb":0.101493,"hr":0.025685,"out":0.655303},"display":{"BB":60,"ERA":"3.30","G":35,"GS":19,"H":163,"HR":13,"IP":158.0,"L":7,"SO":59,"W":10,"team":"DET","year":1979},"name":"Jack Billingham","playerId":"billija01","role":"SP","stamina":0.5016},{"allowed":{"b1":0.168987,"b2":0.049061,"b3":0.005451,"bb":0.130023,"hr":0.018545,"out":0.627933},"display":{"BB":50,"ERA":"3.51","G":31,"GS":14,"H":91,"HR":5,"IP":89.7,"L":6,"SO":64,"W":4,"team":"DET","year":1971},"name":"Dean Chance","playerId":"chancde01","role":"SP","stamina":0.3214},{"allowed":{"b1":0.139133,"b2":0.040393,"b3":0.004488,"bb":0.089175,"hr":0.038886,"out":0.687925},"display":{"BB":37,"ERA":"3.64","G":20,"GS":13,"H":96,"HR":13,"IP":106.3,"L":2,"SO":82,"W":6,"team":"DET","year":1977},"name":"Milt Wilcox","playerId":"wilcomi01","role":"SP","stamina":0.5907},{"allowed":{"b1":0.153137,"b2":0.044459,"b3":0.00494,"bb":0.124901,"hr":0.024555,"out":0.648008},"display":{"BB":98,"ERA":"3.84","G":29,"GS":29,"H":167,"HR":15,"IP":180.7,"L":7,"SO":156,"W":12,"team":"DET","year":1970},"name":"Les Cain","playerId":"cainle01","role":"SP","stamina":0.6922},{"allowed":{"b1":0.17891,"b2":0.051942,"b3":0.005771,"bb":0.076125,"hr":0.044255,"out":0.642997},"display":{"BB":59,"ERA":"3.92","G":32,"GS":32,"H":227,"HR":19,"IP":199.7,"L":12,"SO":88,"W":9,"team":"DET","year":1976},"name":"Vern Ruhle","playerId":"ruhleve01","role":"SP","stamina":0.6933},{"allowed":{"b1":0.158142,"b2":0.045912,"b3":0.005101,"bb":0.089541,"hr":0.054831,"out":0.646473},"display":{"BB":34,"ERA":"3.94","G":22,"GS":10,"H":99,"HR":14,"IP":93.7,"L":6,"SO":58,"W":6,"team":"DET","year":1978},"name":"Bob Sykes","playerId":"sykesbo01","role":"SP","stamina":0.4731},{"allowed":{"b1":0.144293,"b2":0.041892,"b3":0.004655,"bb":0.093368,"hr":0.036204,"out":0.679588},"display":{"BB":33,"ERA":"3.95","G":15,"GS":15,"H":90,"HR":11,"IP":98.0,"L":5,"SO":43,"W":6,"team":"DET","year":1979},"name":"Dan Petry","playerId":"petryda01","role":"SP","stamina":0.7259},{"allowed":{"b1":0.168968,"b2":0.049055,"b3":0.005451,"bb":0.066821,"hr":0.03076,"out":0.678945},"display":{"BB":63,"ERA":"4.00","G":36,"GS":36,"H":254,"HR":16,"IP":252.0,"L":17,"SO":79,"W":16,"team":"DET","year":1976},"name":"Dave Roberts","playerId":"roberda05","role":"SP","stamina":0.7778},{"allowed":{"b1":0.176412,"b2":0.051217,"b3":0.005691,"bb":0.066162,"hr":0.037292,"out":0.663226},"display":{"BB":55,"ERA":"4.03","G":35,"GS":34,"H":225,"HR":22,"IP":203.0,"L":13,"SO":66,"W":14,"team":"DET","year":1973},"name":"Jim Perry","playerId":"perryji01","role":"SP","stamina":0.6444},{"allowed":{"b1":0.168702,"b2":0.048978,"b3":0.005442,"bb":0.077404,"hr":0.039769,"out":0.659705},"display":{"BB":72,"ERA":"4.06","G":38,"GS":34,"H":221,"HR":28,"IP":213.0,"L":13,"SO":101,"W":12,"team":"DET","year":1970},"name":"Joe Niekro","playerId":"niekrjo01","role":"SP","stamina":0.6228},{"allowed":{"b1":0.15433,"b2":0.044806,"b3":0.004978,"bb":0.094885,"hr":0.042171,"out":0.65883},"display":{"BB":85,"ERA":"4.12","G":35,"GS":34,"H":235,"HR":27,"IP":233.7,"L":11,"SO":92,"W":17,"team":"DET","year":1978},"name":"Jim Slaton","playerId":"slatoji01","role":"SP","stamina":0.7418},{"allowed":{"b1":0.170788,"b2":0.049584,"b3":0.005509,"bb":0.062117,"hr":0.03436,"out":0.677642},"display":{"BB":52,"ERA":"4.17","G":38,"GS":28,"H":227,"HR":23,"IP":209.3,"L":18,"SO":60,"W":8,"team":"DET","year":1977},"name":"Fernando Arroyo","playerId":"arroyfe01","role":"SP","stamina":0.6121},{"allowed":{"b1":0.165758,"b2":0.048123,"b3":0.005347,"bb":0.111114,"hr":0.029393,"out":0.640265},"display":{"BB":39,"ERA":"4.37","G":22,"GS":11,"H":84,"HR":7,"IP":80.3,"L":5,"SO":37,"W":4,"team":"DET","year":1973},"name":"Mike Strahler","playerId":"strahmi01","role":"SP","stamina":0.4057},{"allowed":{"b1":0.173166,"b2":0.050274,"b3":0.005586,"bb":0.088695,"hr":0.031449,"out":0.65083},"display":{"BB":66,"ERA":"4.38","G":32,"GS":26,"H":183,"HR":15,"IP":164.3,"L":14,"SO":75,"W":7,"team":"DET","year":1975},"name":"Lerrin LaGrow","playerId":"lagrole01","role":"SP","stamina":0.5706},{"allowed":{"b1":0.142384,"b2":0.041337,"b3":0.004593,"bb":0.079387,"hr":0.048199,"out":0.6841},"display":{"BB":32,"ERA":"4.41","G":18,"GS":16,"H":87,"HR":15,"IP":96.0,"L":6,"SO":74,"W":4,"team":"DET","year":1970},"name":"Earl Wilson","playerId":"wilsoea01","role":"SP","stamina":0.5926},{"allowed":{"b1":0.190238,"b2":0.05523,"b3":0.006137,"bb":0.070458,"hr":0.023595,"out":0.654342},"display":{"BB":47,"ERA":"4.48","G":29,"GS":21,"H":174,"HR":10,"IP":150.7,"L":13,"SO":71,"W":8,"team":"DET","year":1975},"name":"Ray Bare","playerId":"barera01","role":"SP","stamina":0.5773},{"allowed":{"b1":0.154505,"b2":0.044856,"b3":0.004984,"bb":0.148718,"hr":0.032524,"out":0.614413},"display":{"BB":42,"ERA":"4.55","G":15,"GS":10,"H":66,"HR":6,"IP":63.3,"L":4,"SO":39,"W":2,"team":"DET","year":1978},"name":"Steve Baker","playerId":"bakerst01","role":"SP","stamina":0.4691},{"allowed":{"b1":0.157154,"b2":0.045625,"b3":0.005069,"bb":0.06175,"hr":0.044166,"out":0.686236},"display":{"BB":29,"ERA":"4.59","G":27,"GS":15,"H":126,"HR":17,"IP":121.7,"L":4,"SO":83,"W":6,"team":"DET","year":1979},"name":"Pat Underwood","playerId":"underpa01","role":"SP","stamina":0.5007},{"allowed":{"b1":0.160978,"b2":0.046736,"b3":0.005193,"bb":0.072742,"hr":0.061356,"out":0.652995},"display":{"BB":28,"ERA":"4.63","G":14,"GS":14,"H":100,"HR":19,"IP":91.3,"L":5,"SO":52,"W":3,"team":"DET","year":1970},"name":"Denny McLain","playerId":"mclaide01","role":"SP","stamina":0.7249},{"allowed":{"b1":0.154227,"b2":0.044775,"b3":0.004975,"bb":0.115912,"hr":0.031053,"out":0.649058},"display":{"BB":44,"ERA":"5.00","G":30,"GS":11,"H":83,"HR":8,"IP":86.3,"L":5,"SO":47,"W":4,"team":"DET","year":1971},"name":"Mike Kilkenny","playerId":"kilkemi01","role":"SP","stamina":0.3198},{"allowed":{"b1":0.165572,"b2":0.048069,"b3":0.005341,"bb":0.100104,"hr":0.039728,"out":0.641186},"display":{"BB":34,"ERA":"5.09","G":20,"GS":10,"H":86,"HR":7,"IP":81.3,"L":6,"SO":51,"W":4,"team":"DET","year":1976},"name":"Dave Lemanczyk","playerId":"lemanda01","role":"SP","stamina":0.4519},{"allowed":{"b1":0.130582,"b2":0.037911,"b3":0.004212,"bb":0.108358,"hr":0.023361,"out":0.695576},"display":{"BB":15,"ERA":"1.41","G":25,"GS":1,"H":27,"HR":2,"IP":38.3,"L":1,"SO":21,"W":1,"team":"DET","year":1972},"name":"Chris Zachary","playerId":"zachach02","role":"RP","stamina":0.1704},{"allowed":{"b1":0.124061,"b2":0.036018,"b3":0.004002,"bb":0.07614,"hr":0.020658,"out":0.739121},"display":{"BB":39,"ERA":"1.44","G":65,"GS":0,"H":89,"HR":7,"IP":125.3,"L":5,"SO":124,"W":10,"team":"DET","year":1973},"name":"John Hiller","playerId":"hillejo01","role":"RP","stamina":0.2142},{"allowed":{"b1":0.117131,"b2":0.034006,"b3":0.003778,"bb":0.105285,"hr":0.030515,"out":0.709285},"display":{"BB":51,"ERA":"2.41","G":61,"GS":0,"H":95,"HR":12,"IP":127.0,"L":5,"SO":106,"W":10,"team":"DET","year":1979},"name":"Aurelio Lopez","playerId":"lopezau01","role":"RP","stamina":0.2313},{"allowed":{"b1":0.137208,"b2":0.039835,"b3":0.004426,"bb":0.11349,"hr":0.035612,"out":0.669429},"display":{"BB":49,"ERA":"2.71","G":69,"GS":1,"H":91,"HR":11,"IP":113.0,"L":6,"SO":46,"W":11,"team":"DET","year":1971},"name":"Fred Scherman","playerId":"scherfr01","role":"RP","stamina":0.182},{"allowed":{"b1":0.15911,"b2":0.046193,"b3":0.005133,"bb":0.096272,"hr":0.023721,"out":0.669571},"display":{"BB":39,"ERA":"2.89","G":61,"GS":3,"H":96,"HR":6,"IP":112.0,"L":8,"SO":76,"W":9,"team":"DET","year":1972},"name":"Chuck Seelbach","playerId":"seelbch01","role":"RP","stamina":0.204},{"allowed":{"b1":0.197612,"b2":0.057371,"b3":0.006375,"bb":0.127193,"hr":0.008851,"out":0.602598},"display":{"BB":21,"ERA":"3.13","G":24,"GS":0,"H":48,"HR":1,"IP":37.3,"L":4,"SO":18,"W":2,"team":"DET","year":1978},"name":"Steve Foucault","playerId":"foucast01","role":"RP","stamina":0.1728},{"allowed":{"b1":0.134235,"b2":0.038971,"b3":0.00433,"bb":0.122928,"hr":0.025339,"out":0.674197},"display":{"BB":22,"ERA":"3.43","G":22,"GS":0,"H":34,"HR":3,"IP":42.0,"L":2,"SO":23,"W":4,"team":"DET","year":1973},"name":"Bob Miller","playerId":"millebo04","role":"RP","stamina":0.2121},{"allowed":{"b1":0.116141,"b2":0.033718,"b3":0.003746,"bb":0.145309,"hr":0.063883,"out":0.637203},"display":{"BB":51,"ERA":"4.09","G":26,"GS":3,"H":77,"HR":13,"IP":94.7,"L":5,"SO":74,"W":0,"team":"DET","year":1976},"name":"Bill Laxton","playerId":"laxtobi01","role":"RP","stamina":0.4046},{"allowed":{"b1":0.152767,"b2":0.044352,"b3":0.004928,"bb":0.13931,"hr":0.026825,"out":0.631818},"display":{"BB":28,"ERA":"4.22","G":31,"GS":1,"H":47,"HR":4,"IP":49.0,"L":3,"SO":27,"W":0,"team":"DET","year":1971},"name":"Bill Denehy","playerId":"denehbi01","role":"RP","stamina":0.1756},{"allowed":{"b1":0.119944,"b2":0.034822,"b3":0.003869,"bb":0.088145,"hr":0.055183,"out":0.698037},"display":{"BB":25,"ERA":"4.33","G":37,"GS":0,"H":59,"HR":12,"IP":68.7,"L":5,"SO":48,"W":3,"team":"DET","year":1979},"name":"Dave Tobik","playerId":"tobikda01","role":"RP","stamina":0.2062},{"allowed":{"b1":0.173646,"b2":0.050413,"b3":0.005601,"bb":0.119388,"hr":0.02611,"out":0.624842},"display":{"BB":19,"ERA":"4.35","G":20,"GS":0,"H":45,"HR":3,"IP":39.3,"L":3,"SO":24,"W":2,"team":"DET","year":1978},"name":"Jim Crawford","playerId":"crawfji01","role":"RP","stamina":0.2185},{"allowed":{"b1":0.150224,"b2":0.043613,"b3":0.004846,"bb":0.085544,"hr":0.04889,"out":0.666883},"display":{"BB":40,"ERA":"4.45","G":36,"GS":9,"H":116,"HR":16,"IP":115.3,"L":8,"SO":60,"W":3,"team":"DET","year":1975},"name":"Tom Walker","playerId":"walketo02","role":"RP","stamina":0.356},{"allowed":{"b1":0.146621,"b2":0.042567,"b3":0.00473,"bb":0.137115,"hr":0.028916,"out":0.640051},"display":{"BB":29,"ERA":"4.47","G":28,"GS":0,"H":49,"HR":4,"IP":52.3,"L":3,"SO":26,"W":1,"team":"DET","year":1974},"name":"Jim Ray","playerId":"rayji01","role":"RP","stamina":0.2077},{"allowed":{"b1":0.143367,"b2":0.041623,"b3":0.004625,"bb":0.159732,"hr":0.033468,"out":0.617185},"display":{"BB":41,"ERA":"4.64","G":36,"GS":0,"H":63,"HR":5,"IP":66.0,"L":1,"SO":36,"W":3,"team":"DET","year":1976},"name":"Steve Grilli","playerId":"grillst01","role":"RP","stamina":0.2037},{"allowed":{"b1":0.154625,"b2":0.044891,"b3":0.004988,"bb":0.091719,"hr":0.078629,"out":0.625148},"display":{"BB":14,"ERA":"4.67","G":21,"GS":0,"H":40,"HR":8,"IP":34.7,"L":2,"SO":26,"W":0,"team":"DET","year":1975},"name":"Bob Reynolds","playerId":"reynobo01","role":"RP","stamina":0.1834},{"allowed":{"b1":0.163883,"b2":0.047579,"b3":0.005287,"bb":0.118249,"hr":0.033286,"out":0.631716},"display":{"BB":39,"ERA":"4.85","G":43,"GS":0,"H":81,"HR":9,"IP":78.0,"L":1,"SO":55,"W":7,"team":"DET","year":1970},"name":"Daryl Patterson","playerId":"patteda02","role":"RP","stamina":0.2016},{"allowed":{"b1":0.176645,"b2":0.051284,"b3":0.005698,"bb":0.134906,"hr":0.021095,"out":0.610372},"display":{"BB":27,"ERA":"5.00","G":24,"GS":0,"H":52,"HR":3,"IP":45.0,"L":0,"SO":28,"W":3,"team":"DET","year":1973},"name":"Ed Farmer","playerId":"farmeed01","role":"RP","stamina":0.2083}]}
